torch_molecule/__init__.py
torch_molecule/base/__init__.py
torch_molecule/base/base.py
torch_molecule/base/encoder.py
torch_molecule/base/generator.py
torch_molecule/base/old_encoder.py
torch_molecule/base/old_predictor.py
torch_molecule/base/old_predictor2.py
torch_molecule/base/predictor.py
torch_molecule/datasets/__init__.py
torch_molecule/datasets/constant.py
torch_molecule/datasets/load_hf_dataset.py
torch_molecule/datasets/load_local_csv.py
torch_molecule/datasets/data/polymer_gas_permeability.csv.gz
torch_molecule/encoder/constant.py
torch_molecule/encoder/attrmask/__init__.py
torch_molecule/encoder/attrmask/model.py
torch_molecule/encoder/attrmask/modeling_attrmask.py
torch_molecule/encoder/contextpred/__init__.py
torch_molecule/encoder/contextpred/model.py
torch_molecule/encoder/contextpred/modeling_contextpred.py
torch_molecule/encoder/contextpred/utils.py
torch_molecule/encoder/edgepred/__init__.py
torch_molecule/encoder/edgepred/model.py
torch_molecule/encoder/edgepred/modeling_edgepred.py
torch_molecule/encoder/graphmae/__init__.py
torch_molecule/encoder/graphmae/dataloader.py
torch_molecule/encoder/graphmae/model.py
torch_molecule/encoder/graphmae/modeling_graphmae.py
torch_molecule/encoder/infograph/__init__.py
torch_molecule/encoder/infograph/loss_function.py
torch_molecule/encoder/infograph/model.py
torch_molecule/encoder/infograph/modeling_infograph.py
torch_molecule/encoder/infograph/module.py
torch_molecule/encoder/moama/__init__.py
torch_molecule/encoder/moama/model.py
torch_molecule/encoder/moama/modeling_moama.py
torch_molecule/encoder/moama/utils.py
torch_molecule/encoder/pretrained/__init__.py
torch_molecule/encoder/pretrained/modeling_pretrained.py
torch_molecule/encoder/supervised/__init__.py
torch_molecule/encoder/supervised/model.py
torch_molecule/encoder/supervised/modeling_supervised.py
torch_molecule/generator/defog/__init__.py
torch_molecule/generator/defog/extra_features.py
torch_molecule/generator/defog/flow_matching.py
torch_molecule-0.1.7.dist-info/licenses/LICENSE
torch_molecule-0.1.7.dist-info/METADATA
torch_molecule-0.1.7.dist-info/WHEEL
torch_molecule-0.1.7.dist-info/top_level.txt
torch_molecule-0.1.7.dist-info/RECORD
