Metadata-Version: 2.4
Name: torch_molecule
Version: 0.1.7
Summary: Deep learning packages for molecular discovery with a simple sklearn-style interface
Author-email: Gang Liu <gliu7@nd.edu>
License: MIT
Project-URL: Homepage, https://github.com/liugangcode/torch-molecule
Project-URL: Bug Tracker, https://github.com/liugangcode/torch-molecule
Project-URL: Documentation, https://liugangcode.github.io/torch-molecule/
Classifier: Programming Language :: Python :: 3
Classifier: License :: OSI Approved :: MIT License
Classifier: Operating System :: OS Independent
Requires-Python: >=3.8
License-File: LICENSE
Requires-Dist: torch>=2.2.0
Requires-Dist: torch-geometric>=2.6.1
Requires-Dist: numpy
Requires-Dist: huggingface_hub>=0.22.2
Requires-Dist: joblib>=1.3.2
Requires-Dist: networkx>=3.2.1
Requires-Dist: rdkit>=2023.9.5
Requires-Dist: scikit_learn>=1.2.2
Requires-Dist: scipy>=1.14.1
Requires-Dist: tqdm>=4.66.2
Requires-Dist: optuna>=4.0.0
Provides-Extra: dev
Requires-Dist: pytest>=7.0; extra == "dev"
Requires-Dist: black; extra == "dev"
Requires-Dist: isort; extra == "dev"
Requires-Dist: flake8; extra == "dev"
Dynamic: license-file
